Workbook

Sheet Ogólny 
B1: Plant Balanced Scorecard | Z1: Edycja | AB1: 01
C4: Zakład : | P4: Rok | R4: 2024 | U4: =TODAY() -> 46270 | W4: Przygotowany przez
P5: Data rewizji
A6: N
A7: MD | B7: MT | C7: OBSZAR | E7: WSKAŹNIK | H7: Jednostka | I7: Częstotliwość | J7: Typ wskaźnika | K7: Odpowiedzialność | M7: BENCHMARK TYC/SKA | N7: DOPUSZCZALNE LIMITY [%] | O7: =R4 -> 2024 | P7: 44927 | Q7: =DATE(R4,2,1) -> 45323 | R7: =DATE(R4,3,1) -> 45352 | S7: =DATE(R4,4,1) -> 45383 | T7: =DATE(R4,5,1) -> 45413 | U7: =DATE(R4,6,1) -> 45444 | V7: =DATE(R4,7,1) -> 45474 | W7: =DATE(R4,8,1) -> 45505 | X7: =DATE(R4,9,1) -> 45536 | Y7: =DATE(R4,10,1) -> 45566 | Z7: =DATE(R4,11,1) -> 45597 | AA7: =DATE(R4,12,1) -> 45627 | AB7: YTD
F8: Metoda liczenia | G8: Definicja | O8: CEL REZULTAT
A9: GD (SALES) | B9: SPRZEDAŻ | C9: SALES DIRECTOR | E9: WIELKOŚĆ SPRZEDAŻY NETTO | F9: Wielkość sprzedaży netto = Przychody brutto − Rabaty − Zwroty − Skonta Bezpośrednio ze sprawozdań finansowych | G9: Wielkość sprzedaży netto odnosi się do całkowitych przychodów ze sprzedaży produktów lub usług po odjęciu wszelkich rabatów, zwrotów i skont. Jest to miara efektywności sprzedaży i pokazuje, ile firma zarobiła na sprzedaży po uwzględnieniu zniżek i korekt. | H9: min. | I9: Miesiąc | J9: Rozliczeniowy | K9: Sprzedaż | O9: CEL
H10: LC/1000 | O10: Rezultat
E11: WIELKOŚĆ SPRZEDAŻY NETTO (eksport) | F11: j.w., dla sprzedaży eksportowej | G11: Jak wyżej, dla eksportu | H11: min. | I11: Miesiąc | J11: Rozliczeniowy | O11: CEL
H12: LC/1000 | O12: Rezultat
E13: WIELKOŚĆ SPRZEDAŻY NETTO (kraj) | F13: j.w., dla sprzedaży krajowej | G13: Jak wyżej, dla sprzedaży krajowej | H13: min. | I13: Miesiąc | J13: Rozliczeniowy | O13: CEL
H14: LC/1000 | O14: Rezultat
E15: WIELKOŚĆ SPRZEDAŻY NETTO (narastająco) | F15: j.w., narastająco | G15: Jak wyżej | H15: min. | I15: Miesiąc narastająco | J15: Rozliczeniowy | K15: Sprzedaż | O15: CEL
H16: LC/1000 | O16: Rezultat
E17: WIELKOŚĆ SPRZEDAŻY NETTO (w odniesieniu do budżetu) | F17: WIELKOŚĆ SPRZEDAŻY NETTO (w odniesieniu do budżetu) = Sprzedaż rzeczywista / Sprzedaż netto budżetowana x100% | G17: Wskaźnik, który mierzy, jak dobrze rzeczywista sprzedaż netto realizuje założenia budżetowe. Jest to wskaźnik wykorzystywany do oceny skuteczności zarządzania sprzedażą w kontekście zaplanowanych celów finansowych. | H17: min. | I17: Miesiąc | J17: Rozliczeniowy | K17: Sprzedaż | O17: CEL
H18: % | O18: Rezultat
E19: WIELKOŚĆ SPRZEDAŻY NETTO (w odniesieniu do prognozy) | F19: WIELKOŚĆ SPRZEDAŻY NETTO (w odniesieniu do prognozy) = Sprzedaż rzeczywista / Sprzedaż netto prognozowana x100% | G19: Wskaźnik, który mierzy, jak dobrze rzeczywista sprzedaż netto realizuje założenia prognozy. Jest to wskaźnik wykorzystywany do oceny skuteczności zarządzania sprzedażą w kontekście zaplanowanych celów finansowych. | H19: min. | I19: Miesiąc | J19: Rozliczeniowy | K19: Sprzedaż | O19: CEL
H20: LC/1000 | O20: Rezultat
E21: LICZBA NOWYCH WOLUMENÓW (BEZ MODYFIKACJI OBECNYCH) | F21: Kryterium "nowego wolumenu" - produkt który został wprowadzony na rynek po raz pierwszy w danym okresie i nie jest modyfikacją istniejącego produktu (np. nowe warianty kolorystyczne, wersje rozwojowe produktu, itp. nie są uwzględniane) | G21: Liczba sprzedanych nowych wolumenów odnosi się do liczby nowych produktów po raz pierwszy w danym okresie, które nie są modyfikacjami ani ulepszeniami istniejących produktów. Ten wskaźnik koncentruje się na innowacyjnych lub zupełnie nowych propozycjach wartości w ofercie firmy, będących wynikiem rozwoju nowych produktów lub usług. | H21: min. | I21: Miesiąc | J21: Informacyjny | K21: Sprzedaż | O21: CEL
H22: [szt.] | O22: Rezultat
E23: LICZBA NOWYCH KLIENTÓW | F23: Liczba nowych klientów = Liczba unikalnych klient ów w okresie − Liczba klientów już istniejących Kryterium "nowego klienta" - Klient, który dokonał pierwszego zakupu w danym okresie i nie figurował wcześniej w bazie klientów. | G23: Wskaźnik określający liczbę unikalnych klientów, którzy po raz pierwszy dokonali zakupu lub skorzystali z usług firmy w określonym okresie czasu. Jest to kluczowy wskaźnik w perspektywie klienta w ramach Balanced Scorecard (BSC), który odzwierciedla zdolność firmy do pozyskiwania nowych odbiorców swoich produktów lub usług. | H23: max. | I23: Miesiąc | J23: Informacyjny | K23: Sprzedaż | O23: CEL
H24: [szt.] | O24: Rezultat
C25: RSM/KAM | E25: WIELKOŚĆ SPRZEDAŻY (indywidualna) | F25: Wielkość sprzedaży indywidualna = Całkowita wartość sprzedaży przypisana do indywidualnego klienta/produktu/usługi | G25: Sprzedaż indywidualna odnosi się do wielkości sprzedaży powiązanej z określonym klientem, produktem lub usługą. | H25: min. | I25: Miesiąc | J25: Rozliczeniowy | K25: Sprzedaż | O25: CEL
H26: m2 | O26: Rezultat
E27: ŚREDNIA MARŻA | F27: Średnia marża = (Przychody ze sprzedaży - Koszty sprzedaży) / Przychody ze sprzedaży × 100 | G27: Średnia marża to różnica między przychodami ze sprzedaży a kosztami sprzedaży, wyrażona procentowo. | H27: max. | I27: Miesiąc | J27: Rozliczeniowy | K27: Sprzedaż | O27: CEL
H28: % | O28: Rezultat
E29: LICZBA NOWYCH WOLUMENÓW (BEZ MODYFIKACJI OBECNYCH) | F29: Liczba nowych wolumenów = Liczba nowych produktów lub usług wprowadzonych do sprzedaży w danym okresie | G29: Liczba nowych wolumenów to liczba nowych produktów lub usług wprowadzonych na rynek, bez modyfikacji istniejących. | H29: min. | I29: Miesiąc | J29: Informacyjny | O29: CEL
H30: [m2] | O30: Rezultat
E31: POZIOM OTWARTYCH ZAMÓWIEŃ | F31: Poziom otwartych zamówień = Łączna liczba zamówień niezrealizowanych w danym okresie | G31: Poziom otwartych zamówień mierzy liczbę zamówień klientów, które nie zostały jeszcze zrealizowane. | H31: min. | I31: Miesiąc | J31: Rozliczeniowy | K31: Sprzedaż | O31: CEL
H32: m2 | O32: Rezultat
E33: PROCENT REFAKTUROWANIA NARZĘDZI | F33: Procent refakturowania narzędzi = (Wartość narzędzi zrefakturowanych / Wartość wszystkich narzędzi) × 100 | G33: Procent refakturowania narzędzi mierzy udział narzędzi zrefakturowanych w stosunku do wszystkich używanych narzędzi. | H33: min. | I33: Miesiąc narastajaco | J33: Rozliczeniowy | K33: Sprzedaż | O33: CEL
H34: % | O34: Rezultat
E35: LICZBA NOWYCH KLIENTÓW | F35: Liczba nowych klientów = Klienci pozyskani w danym okresie | G35: wskaźnik mierzący ilość nowych klientów pozyskanych przez firmę w określonym czasie. Odzwierciedla zdolność firmy do przyciągania nowych odbiorców i poszerzania bazy klientów. | H35: min | I35: Miesiąc | J35: Rozliczeniowy | K35: Sprzedaż | O35: CEL
H36: szt. | O36: Rezultat
C37: CS | E37: POZIOM SATYSFAKCJI KLIENTÓW | F37: Nie ma uniwersalnego wzoru, jednak poziom satysfakcji klientów często mierzy się za pomocą ankiet (np. Net Promoter Score - NPS), które pytają klientów o ich poziom zadowolenia na skali punktowej. NPS = %promotorów − %krytyków | G37: wskaźnik mierzący stopień zadowolenia klientów z produktów, usług lub ogólnej współpracy z firmą. Jest to kluczowy wskaźnik jakości obsługi klienta i lojalności klientów wobec firmy. | H37: min. | I37: Kwartał | J37: Rozliczeniowy | O37: CEL
H38: % | O38: Rezultat
E39: STAN MAGAZYNU PALET (ŚREDNIA LICZBA PALET NIE WIĘCEJ NIŻ 5% POWYŻEJ LIMITU) | F39: Stan magazynu palet = Średnia liczba palet w magazynie / Ustalony limit palet ×100% | G39: wskaźnik logistyczny monitorujący, jak skutecznie firma utrzymuje zapasy palet w magazynie, zapewniając, że ich liczba nie przekracza ustalonego limitu o więcej niż 5%. | H39: min. | I39: Miesiąc | J39: Rozliczeniowy | O39: CEL
H40: szt. | O40: Rezultat
E41: NALEŻNOŚCI PRZETERMINOWANA POWYŻEJ 7 DNI | F41: Należności przeterminowane powyżej 7 dni = Wartość przeterminowanych należności powyżej 7 dni / Całkowita wartość należności ×100% | G41: wskaźnik finansowy mierzący wartość zobowiązań klientów wobec firmy, które nie zostały uregulowane w ciągu 7 dni od ustalonego terminu płatności. | H41: max. | I41: Miesiąc | J41: Rozliczeniowy | O41: CEL
H42: LC/1000 | O42: Rezultat
C43: DPW | E43: LICZBA WDROŻEŃ FTQ (PPP) | F43: FTQ = Liczba projekt ów wdrożonych bez poprawek / Całkowita liczba wdrożonych projektów ×100% | G43: wskaźnik mierzący liczbę projektów lub produktów, które zostały wdrożone z pełną zgodnością z wymogami jakościowymi już za pierwszym razem, bez konieczności poprawek czy dodatkowych działań. | H43: min. | I43: Miesiąc | J43: Rozliczeniowy | K43: Technologia | O43: CEL
H44: Liczba | O44: Rezultat
E45: LICZBA OPTYMALIZACJI PORTFOLIO KLIENTA (KAIZEN WEWN.) | F45: ∑Zrealizowane inicjatywy optymalizacyjne w danym okresie | G45: wskaźnik mierzący liczbę wewnętrznych inicjatyw optymalizacyjnych, które mają na celu poprawę oferty lub obsługi klienta zgodnie z zasadami Kaizen – ciągłego doskonalenia. Wskaźnik ten monitoruje działania mające na celu zwiększenie efektywności, wartości oferty oraz zadowolenia klientów. | H45: min. | I45: Kwartał | J45: Informacyjny | K45: Technologia | O45: CEL
H46: szt. | O46: Rezultat
E47: Wielkość portfela zamówień | F47: Wielkość portfela zamówień =∑wartość wszystkich otwartych zamówień | G47: wskaźnik mierzący łączną wartość, które firma posiada w danym okresie, ale jeszcze nie zostały zrealizowane. Jest to kluczowy wskaźnik prognozujący przyszłe przychody i poziom obciążenia produkcji lub logistyki. | H47: min | I47: Miesiąc | J47: Rozliczeniowy | K47: Sprzedaż | O47: CEL
H48: LC/1000 | O48: Rezultat
E49: Wskaźnik book/bill | F49: Wskaźnik book/bill = Wartość nowych zamówień / Wartość fakturowanych sprzedaży ​ | G49: wskaźnik mierzący stosunek wartości nowych zamówień (bookings) do fakturowanych sprzedaży (billings) w danym okresie. Używany jest do oceny dynamiki sprzedaży oraz przyszłych perspektyw finansowych przedsiębiorstwa. | I49: Miesiąc | J49: Rozliczeniowy | K49: Sprzedaż | O49: CEL
O50: Rezultat
E51: Koszt sprzedaży do wielkości sprzedaży | F51: Koszt sprzedaż y do wielkości sprzedaży = Koszt sprzedanych towarów (COGS) / Przychody ze sprzedaży ×100% | G51: wskaźnik finansowy określający, jaki procent przychodów ze sprzedaży stanowi koszt uzyskania tej sprzedaży (czyli koszt sprzedanych towarów lub usług - COGS). Używany jest do oceny rentowności działalności operacyjnej przedsiębiorstwa. | I51: Miesiąc | J51: Rozliczeniowy | K51: Sprzedaż | O51: CEL
O52: Rezultat
E53: Koszt wytworzenia/ Przychód | F53: Koszt wytworzenia/Przychód = Koszt wytworzenia produktów / Przychód ze sprzedaży ×100% | G53: wskaźnik finansowy, który mierzy stosunek kosztów wytworzenia produktów lub usług (czyli kosztów operacyjnych związanych z produkcją) do uzyskanych przychodów ze sprzedaży tych produktów lub usług. Służy do oceny efektywności kosztowej przedsiębiorstwa. | I53: Miesiąc | J53: Rozliczeniowy | K53: Sprzedaż | O53: CEL
O54: Rezultat
E55: TERMINOWE FAKTUROWANIE (MAX 24H) | F55: Terminowe fakturowanie (%) = Liczba faktur wystawionych w ciągu 24h / Całkowita liczba faktur ×100% | G55: wskaźnik operacyjny mierzący, jak skutecznie firma wystawia faktury w ciągu maksymalnie 24 godzin od dostarczenia towaru lub zakończenia usługi. Służy do oceny efektywności procesów księgowych i fakturowania. | H55: min | I55: Miesiąc | J55: Rozliczeniowy | K55: Sprzedaż | O55: CEL
H56: % | O56: Rezultat
E57: Liczba błędów zgłaszanych przez klientów po wdrożeniu produktu | G57: wskaźnik jakościowy mierzący ilość problemów, wad lub niezgodności zgłoszonych przez klientów po wprowadzeniu produktu na rynek lub jego implementacji. Służy do oceny jakości produktu oraz efektywności procesu wdrożenia. | H57: max | I57: Miesiąc | J57: Rozliczeniowy | K57: Sprzedaż | O57: CEL
H58: szt. | O58: Rezultat
E59: ŚREDNI CZAS REAKCJI NA OFERTĘ SPRZEDAŻOWĄ CZĘŚCI | G59: wskaźnik operacyjny, który mierzy średni czas, jaki firma potrzebuje, aby odpowiedzieć na zapytanie ofertowe dotyczące sprzedaży części zamiennych lub komponentów. Wskaźnik ten odnosi się do efektywności obsługi klienta i sprzedaży. | H59: max | I59: Miesiąc | J59: Rozliczeniowy | K59: Sprzedaż | O59: CEL
H60: dni | O60: Rezultat
E61: LICZBA ZLECEŃ SERWISOWYCH | G61: wskaźnik mierzący całkowitą liczbę zleceń serwisowych, które firma realizuje w danym okresie. Może obejmować zarówno zaplanowane działania konserwacyjne, jak i zlecenia wynikające z awarii lub problemów zgłoszonych przez klientów. | H61: min | I61: Miesiąc | J61: Rozliczeniowy | K61: Sprzedaż | O61: CEL
H62: szt. | O62: Rezultat
B63: Growth Officer | E63: KOSZTY CAPEX - SKUMULOWANA WARTOŚĆ | F63: Skumulowane CAPEX = ∑(Wydatki inwestycyjne w danym okresie) | G63: wskaźnik mierzący łączną kwotę wydatków inwestycyjnych (CAPEX) poniesionych przez firmę w określonym okresie, obejmujących zakup aktywów trwałych, takich jak sprzęt, nieruchomości czy infrastruktura. | H63: max. | I63: Narastająco | J63: Informacyjny | O63: CEL
H64: LC/1000 | O64: Rezultat
E65: % REALIZACJI BUDŻETU INWESTYCYJNEGO - SKUMULOWANE | F65: %Realizacji budżetu inwestycyjnego - skumulowane = (Skumulowane wydatki inwestycyjne / Skumulowany budżet inwestycyjny)×100 | G65: wskaźnik pokazujący, w jakim stopniu skumulowane wydatki inwestycyjne (CAPEX) w danym okresie zostały zrealizowane w stosunku do skumulowanego budżetu inwestycyjnego. | H65: max. | I65: Miesiąc | J65: Rozliczeniowy | O65: CEL
H66: % | O66: Rezultat
E67: ROI PRE-INWESTYCYJNE | F67: ROI pre-inwestycyjne =(Prognozowany zysk netto z inwestycji / Szacowane koszty inwestycji)×100 | G67: wskaźnik szacujący spodziewany zwrot z inwestycji przed jej realizacją. Jego celem jest ocena potencjalnej opłacalności inwestycji, zanim zostaną poniesione wydatki. | H67: min. | I67: Kwatalny | J67: Informacyjny | O67: CEL
H68: lata | O68: Rezultat
E69: ROI POST-INWESTYCYJNE | F69: ROI post-inwestycyjne =( Rzeczywisty zysk netto z inwestycji / Rzeczywisy koszty inwestycji )×100 | G69: wskaźnik mierzący rzeczywisty zwrot z inwestycji po jej zakończeniu, na podstawie uzyskanych wyników finansowych. Służy do oceny efektywności poniesionych wydatków inwestycyjnych w porównaniu do uzyskanych korzyści. | H69: min. | I69: Kwatalny | J69: Informacyjny | O69: CEL
H70: lata | O70: Rezultat
E71: LICZBA PROJEKTÓW INWESTYCYJNYCH | F71: Liczba projektów inwestycyjnych | G71: wskaźnik mierzący całkowitą liczbę rozpoczętych, realizowanych lub zakończonych projektów inwestycyjnych w danym okresie. Obejmuje wszystkie projekty związane z rozwojem, zakupem aktywów trwałych lub modernizacją istniejących zasobów. | H71: max. | I71: Narastająco | J71: Informacyjny | O71: CEL
H72: szt. | O72: Rezultat
E73: % REALIZACJI PROJEKTÓW INWESTYCYJNYCH | F73: %Realizacji projektów inwestycyjnych = (Liczba zakończonych projektów zgodnie z planem / Całkowita liczba projektów inwestycyjnych w danym okresie)×100 | G73: wskaźnik mierzący, jaki procent rozpoczętych projektów inwestycyjnych zostało zakończonych zgodnie z założonymi terminami, budżetem i zakresem w danym okresie. | H73: max. | I73: Narastająco | J73: Rozliczeniowy | K73: COO | O73: CEL
H74: % | O74: Rezultat
B75: Product Manager | E75: Marża brutto zarządzanej grupy produktowej | F75: Marża brutto =(przychody ze sprzedaży - Koszty produkcji) /przychodzy ze sprzedaży x100% | G75: Wskaźnik ten mierzy rentowność zarządzanej grupy produktowej, wyrażoną jako różnica między przychodami ze sprzedaży a kosztem produkcji. | H75: min. | I75: Miesiąc | J75: Rozliczeniowy | K75: COO | O75: CEL
H76: % | O76: Rezultat
E77: Wskaźnik przychodu na grupę produktową | F77: Revenue per Product = Całkowite przychody produktu | G77: Obrazuje, jak skutecznie produkt generuje przychody w porównaniu do planowanych założeń. | H77: min. | I77: Miesiąc | J77: Rozliczeniowy | K77: COO | O77: CEL
H78: LC/1000 | O78: Rezultat
E79: Customer Acquisition Cos | F79: CAC = Całkowite koszty marketingu i sprzedaży / Liczba po zyskanych klientów | G79: (CAC): Koszt pozyskania nowego klienta dla produktu. Wskaźnik ten pomaga ocenić efektywność strategii marketingowych i sprzedażowych produktu. | H79: max. | I79: Miesiąc | J79: Rozliczeniowy | K79: COO | O79: CEL
H80: LC/1000 | O80: Rezultat
E81: Czas wprowadzenia nowego produktu na rynek | F81: Time to Market = Data wprowadzenia na rynek − Data rozpoczęcia projektu | G81: (Time to Market): Mierzy szybkość, z jaką zespół jest w stanie przejść od pomysłu do wdrożenia produktu na rynek. Krótszy czas wprowadzenia może być wskaźnikiem efektywnego zarządzania projektem. | H81: max. | I81: Miesiąc | J81: Rozliczeniowy | K81: COO | O81: CEL
H82: dni | O82: Rezultat
B83: R&D | E83: Koszt wdrożeń vs budżet | F83: Koszt wdrożeń vs budżet =(Rzeczywisty koszt wdrożeń / Planowany budżet wdrożeń)×100 | G83: wskaźnik porównujący rzeczywiste koszty związane z realizacją wdrożeń (np. projektów inwestycyjnych, technologicznych) z planowanym budżetem przeznaczonym na te wdrożenia. Wskaźnik ten służy do oceny efektywności finansowej wdrożeń. | H83: max | I83: Miesiąc | J83: Rozliczeniowy | K83: Sprzedaż | O83: CEL
H84: % | O84: Rezultat
E85: CAPEX | F85: bezpośrednio z raportów finansowych | G85: Narastająco realizacja CAPEX | H85: max | I85: Miesiąc | J85: Rozliczeniowy | K85: Sprzedaż | O85: CEL
H86: LC/1000 | O86: Rezultat
E87: Wykonanie CAPEX | F87: Wykonanie CAPEX = Rzeczywiste wydatki CAPEX / Zaplanowane wydatki CAPEX × 100% | G87: wskaźnik mierzący realizację planowanych nakładów inwestycyjnych (CAPEX) w stosunku do faktycznie poniesionych wydatków kapitałowych. CAPEX (Capital Expenditures) odnosi się do wydatków na nabycie lub modernizację długoterminowych aktywów firmy, takich jak budynki, maszyny czy technologie. | H87: max | I87: Miesiąc | J87: Rozliczeniowy | K87: Sprzedaż | O87: CEL
H88: % | O88: Rezultat
E89: Koszty R&D | G89: wskaźnik finansowy, który mierzy wydatki firmy na badania i rozwój nowych produktów, technologii lub procesów. Odzwierciedla poziom inwestycji firmy w innowacje i rozwój nowych rozwiązań. | K89: Sprzedaż | O89: CEL
O90: Rezultat
E91: TPR Zaplanowane/ zrealizowane (JIRA) | F91: TPR = Liczba zrealizowanych zadań / Liczba zaplanowanych zadań x 100% | G91: wskaźnik mierzący stopień realizacji zadań w odniesieniu do planowanych zadań w systemie zarządzania projektami, takim jak JIRA. TPR (Task Performance Ratio) określa, jaka część zaplanowanych zadań została faktycznie zrealizowana w określonym czasie. | H91: min | I91: 2 tygodnie | J91: Rozliczeniowy | K91: Sprzedaż | O91: CEL
H92: % | O92: Rezultat
B93: Dyrektor Zakupy | E93: REALIZACJA BUDŻETU ZAKUPÓW (W PODZIALE NA KATEGORIE) / WYDATKI SKONSOLIDOWANE | F93: Realizacja budżetu zakupów = Rzeczywiste wydatki w kategorii/Planowane wydatki w kategorii × 100% | G93: wskaźnik finansowy mierzący, jak dobrze firma realizuje zaplanowany budżet zakupów w podziale na kategorie zakupowe, w odniesieniu do rzeczywistych, skonsolidowanych wydatków. | H93: min. | I93: Miesiąc | J93: Rozliczeniowy | K93: Sprzedaż | O93: CEL
H94: % | O94: Rezultat
E95: OSZCZĘDNOŚCI ZAKUPOWE (% / wartość) | F95: Oszczędności zakupowe (%) =(Rzeczywisty koszt zakupów - Planowany koszt zakupów) / Planowany koszt zakupów ×100% | G95: wskaźnik finansowy mierzący procentowy udział zaoszczędzonych kosztów związanych z zakupem materiałów, surowców lub usług w stosunku do planowanego budżetu zakupowego. | H95: min. | I95: Miesiąc | J95: Rozliczeniowy | K95: Sprzedaż | O95: CEL
H96: LC/1000 | O96: Rezultat
E97: ROTACJA ZOBOWIĄZAŃ | F97: Rotacja zobowiązań = Zakupy od dostawców / Średnie zobowiązania handlowe | G97: wskaźnik finansowy mierzący, jak szybko przedsiębiorstwo reguluje swoje zobowiązania wobec dostawców. Pokazuje, ile razy w ciągu danego okresu firma spłaca swoje zobowiązania handlowe | H97: max | I97: Miesiąc | J97: Rozliczeniowy | K97: Sprzedaż | O97: CEL
H98: dni | O98: Rezultat
E99: WARTOŚĆ ZAPASÓW | F99: bezpośrednio z raportów finansowych | G99: wskaźnik finansowy określający łączną wartość posiadanych przez firmę materiałów, surowców, produktów w toku oraz towarów gotowych do sprzedaży na dany moment. | H99: min. | I99: Miesiąc | J99: Rozliczeniowy | K99: Sprzedaż | O99: CEL
H100: LC/1000 | O100: Rezultat
E101: KONSUMPCJA MATERIAŁÓW | F101: bezpośrednio z raportów finansowych | G101: wskaźnik finansowy mierzący wartość zużytych materiałów w procesie produkcji w danym okresie. Obejmuje surowce i materiały, które zostały przekształcone w produkty gotowe lub częściowo gotowe. | H101: max. | I101: Miesiąc | J101: Rozliczeniowy | K101: Sprzedaż | O101: CEL
H102: LC/1000 | O102: Rezultat
...

Sheet Arkusz1
A4: jak rozliczać nowy wolumne?

Sheet Karta wskaźnika PRZYKŁAD
A1: Sprzedaż netto | G1: Lata: | H1: ='Ogólny '!R4 -> 2024
A23: UWAGA - jeśli istnieje osobny plan działania lub opracowany dokument analizy przyczyny pierwotnej, w komórce "Komentarze" wystarczy przywołać dany dokument (nie ma potrzeby powielania informacji i działań).
A25: Miesiąc | B25: Czy osiągnięto cel? | C25: Czy wymagane są działania? | D25: Opis problemu | E25: Główna przyczyna | F25: Opis działań | G25: Odpowiedzialność | H25: Data zakończenia | J25: Komentarze | K25: Status (OTWARTY/ ZAMKNIĘTY)
A26: 44927
A27: 44958
A28: 44986
A29: 45017
A30: 45047
A31: 45078
A32: 45108
A33: 45139
A34: 45170
A35: 45200
A36: 45231
A37: 45261

Sheet Sprzedaż netto narastająco
A1: Sprzedaż netto narastająco | G1: Lata: | H1: ='Ogólny '!R4 -> 2024
I2: 1
A23: UWAGA - jeśli istnieje osobny plan działania lub opracowany dokument analizy przyczyny pierwotnej, w komórce "Komentarze" wystarczy przywołać dany dokument (nie ma potrzeby powielania informacji i działań).
A25: Miesiąc | B25: Czy osiągnięto cel? | C25: Czy wymagane są działania? | D25: Opis problemu | E25: Główna przyczyna | F25: Opis działań | G25: Odpowiedzialność | H25: Data zakończenia | J25: Komentarze | K25: Status (OTWARTY/ ZAMKNIĘTY)
A26: 43466
A27: 43497
A28: 43525
A29: 43556
A30: 43586
A31: 43617
A32: 43647
A33: 43678
A34: 43709
A35: 43739
A36: 43770
A37: 43800

Sheet Poziom przyjętych zamówień
A1: Poziom przyjętych zamówień | G1: Lata: | H1: ='Ogólny '!R4 -> 2024
A23: UWAGA - jeśli istnieje osobny plan działania lub opracowany dokument analizy przyczyny pierwotnej, w komórce "Komentarze" wystarczy przywołać dany dokument (nie ma potrzeby powielania informacji i działań).
A25: Miesiąc | B25: Czy osiągnięto cel? | C25: Czy wymagane są działania? | D25: Opis problemu | E25: Główna przyczyna | F25: Opis działań | G25: Odpowiedzialność | H25: Data zakończenia | J25: Komentarze | K25: Status (OTWARTY/ ZAMKNIĘTY)
A26: 43466
A27: 43497
A28: 43525
A29: 43556
A30: 43586
A31: 43617
A32: 43647
A33: 43678
A34: 43709
A35: 43739
A36: 43770
A37: 43800

Sheet Zużycie materiałów
A1: Zużycie materiałów | G1: Lata: | H1: ='Ogólny '!R4 -> 2024
A23: UWAGA - jeśli istnieje osobny plan działania lub opracowany dokument analizy przyczyny pierwotnej, w komórce "Komentarze" wystarczy przywołać dany dokument (nie ma potrzeby powielania informacji i działań).
A25: Miesiąc | B25: Czy osiągnięto cel? | C25: Czy wymagane są działania? | D25: Opis problemu | E25: Główna przyczyna | F25: Opis działań | G25: Odpowiedzialność | H25: Data zakończenia | J25: Komentarze | K25: Status (OTWARTY/ ZAMKNIĘTY)
A26: 43466
A27: 43497
A28: 43525
A29: 43556
A30: 43586
A31: 43617
A32: 43647
A33: 43678
A34: 43709
A35: 43739
A36: 43770
A37: 43800

Sheet Odpad technologiczny jakościowy
A1: Odpad technologiczny/jakościowy | G1: Lata: | H1: ='Ogólny '!R4 -> 2024
A23: UWAGA - jeśli istnieje osobny plan działania lub opracowany dokument analizy przyczyny pierwotnej, w komórce "Komentarze" wystarczy przywołać dany dokument (nie ma potrzeby powielania informacji i działań).
A25: Miesiąc | B25: Czy osiągnięto cel? | C25: Czy wymagane są działania? | D25: Opis problemu | E25: Główna przyczyna | F25: Opis działań | G25: Odpowiedzialność | H25: Data zakończenia | J25: Komentarze | K25: Status (OTWARTY/ ZAMKNIĘTY)
A26: 43466
A27: 43497
A28: 43525
A29: 43556
A30: 43586
A31: 43617
A32: 43647
A33: 43678
A34: 43709
A35: 43739
A36: 43770
A37: 43800

Sheet Kary
A1: Kary | G1: Lata: | H1: ='Ogólny '!R4 -> 2024
A23: UWAGA - jeśli istnieje osobny plan działania lub opracowany dokument analizy przyczyny pierwotnej, w komórce "Komentarze" wystarczy przywołać dany dokument (nie ma potrzeby powielania informacji i działań).
A25: Miesiąc | B25: Czy osiągnięto cel? | C25: Czy wymagane są działania? | D25: Opis problemu | E25: Główna przyczyna | F25: Opis działań | G25: Odpowiedzialność | H25: Data zakończenia | J25: Komentarze | K25: Status (OTWARTY/ ZAMKNIĘTY)
A26: 43466
A27: 43497
A28: 43525
A29: 43556
A30: 43586
A31: 43617
A32: 43647
A33: 43678
A34: 43709
A35: 43739
A36: 43770
A37: 43800

Sheet Koszt pracy bezpośredniej
A1: Koszt pracy bezpośredniej (udział) | G1: Lata: | H1: ='Ogólny '!R4 -> 2024
A23: UWAGA - jeśli istnieje osobny plan działania lub opracowany dokument analizy przyczyny pierwotnej, w komórce "Komentarze" wystarczy przywołać dany dokument (nie ma potrzeby powielania informacji i działań).
A25: Miesiąc | B25: Czy osiągnięto cel? | C25: Czy wymagane są działania? | D25: Opis problemu | E25: Główna przyczyna | F25: Opis działań | G25: Odpowiedzialność | H25: Data zakończenia | J25: Komentarze | K25: Status (OTWARTY/ ZAMKNIĘTY)
A26: 43466
A27: 43497
A28: 43525
A29: 43556
A30: 43586
A31: 43617
A32: 43647
A33: 43678
A34: 43709
A35: 43739
A36: 43770
A37: 43800

Sheet Koszt pracy niebezpośr.-prod.
A1: Koszt pracy niebezpośrednio-produkcyjnej | G1: Lata: | H1: ='Ogólny '!R4 -> 2024
A23: UWAGA - jeśli istnieje osobny plan działania lub opracowany dokument analizy przyczyny pierwotnej, w komórce "Komentarze" wystarczy przywołać dany dokument (nie ma potrzeby powielania informacji i działań).
A25: Miesiąc | B25: Czy osiągnięto cel? | C25: Czy wymagane są działania? | D25: Opis problemu | E25: Główna przyczyna | F25: Opis działań | G25: Odpowiedzialność | H25: Data zakończenia | J25: Komentarze | K25: Status (OTWARTY/ ZAMKNIĘTY)
A26: 43466
A27: 43497
A28: 43525
A29: 43556
A30: 43586
A31: 43617
A32: 43647
A33: 43678
A34: 43709
A35: 43739
A36: 43770
A37: 43800

Sheet Koszt transportu out
A1: Koszt transportu out | G1: Lata: | H1: ='Ogólny '!R4 -> 2024
A23: UWAGA - jeśli istnieje osobny plan działania lub opracowany dokument analizy przyczyny pierwotnej, w komórce "Komentarze" wystarczy przywołać dany dokument (nie ma potrzeby powielania informacji i działań).
A25: Miesiąc | B25: Czy osiągnięto cel? | C25: Czy wymagane są działania? | D25: Opis problemu | E25: Główna przyczyna | F25: Opis działań | G25: Odpowiedzialność | H25: Data zakończenia | J25: Komentarze | K25: Status (OTWARTY/ ZAMKNIĘTY)
A26: 43466
A27: 43497
A28: 43525
A29: 43556
A30: 43586
A31: 43617
A32: 43647
A33: 43678
A34: 43709
A35: 43739
A36: 43770
A37: 43800

Sheet Koszt transportu in
A1: Koszt transportu in | G1: Lata: | H1: ='Ogólny '!R4 -> 2024
A23: UWAGA - jeśli istnieje osobny plan działania lub opracowany dokument analizy przyczyny pierwotnej, w komórce "Komentarze" wystarczy przywołać dany dokument (nie ma potrzeby powielania informacji i działań).
A25: Miesiąc | B25: Czy osiągnięto cel? | C25: Czy wymagane są działania? | D25: Opis problemu | E25: Główna przyczyna | F25: Opis działań | G25: Odpowiedzialność | H25: Data zakończenia | J25: Komentarze | K25: Status (OTWARTY/ ZAMKNIĘTY)
A26: 43466
A27: 43497
A28: 43525
A29: 43556
A30: 43586
A31: 43617
A32: 43647
A33: 43678
A34: 43709
A35: 43739
A36: 43770
A37: 43800

Sheet Wynagrodzenie kadry
A1: Wynagrodzenie kadry | G1: Lata: | H1: ='Ogólny '!R4 -> 2024
A23: UWAGA - jeśli istnieje osobny plan działania lub opracowany dokument analizy przyczyny pierwotnej, w komórce "Komentarze" wystarczy przywołać dany dokument (nie ma potrzeby powielania informacji i działań).
A25: Miesiąc | B25: Czy osiągnięto cel? | C25: Czy wymagane są działania? | D25: Opis problemu | E25: Główna przyczyna | F25: Opis działań | G25: Odpowiedzialność | H25: Data zakończenia | J25: Komentarze | K25: Status (OTWARTY/ ZAMKNIĘTY)
A26: 43466
A27: 43497
A28: 43525
A29: 43556
A30: 43586
A31: 43617
A32: 43647
A33: 43678
A34: 43709
A35: 43739
A36: 43770
A37: 43800

Sheet Marża bezpośrednia
A1: Marża bezpośrednia | G1: Lata: | H1: ='Ogólny '!R4 -> 2024
A23: UWAGA - jeśli istnieje osobny plan działania lub opracowany dokument analizy przyczyny pierwotnej, w komórce "Komentarze" wystarczy przywołać dany dokument (nie ma potrzeby powielania informacji i działań).
A25: Miesiąc | B25: Czy osiągnięto cel? | C25: Czy wymagane są działania? | D25: Opis problemu | E25: Główna przyczyna | F25: Opis działań | G25: Odpowiedzialność | H25: Data zakończenia | J25: Komentarze | K25: Status (OTWARTY/ ZAMKNIĘTY)
A26: 43466
A27: 43497
A28: 43525
A29: 43556
A30: 43586
A31: 43617
A32: 43647
A33: 43678
A34: 43709
A35: 43739
A36: 43770
A37: 43800

Sheet Koszty wydziałowe
A1: Koszty wydziałowe | G1: Lata: | H1: ='Ogólny '!R4 -> 2024
A23: UWAGA - jeśli istnieje osobny plan działania lub opracowany dokument analizy przyczyny pierwotnej, w komórce "Komentarze" wystarczy przywołać dany dokument (nie ma potrzeby powielania informacji i działań).
A25: Miesiąc | B25: Czy osiągnięto cel? | C25: Czy wymagane są działania? | D25: Opis problemu | E25: Główna przyczyna | F25: Opis działań | G25: Odpowiedzialność | H25: Data zakończenia | J25: Komentarze | K25: Status (OTWARTY/ ZAMKNIĘTY)
A26: 43466
A27: 43497
A28: 43525
A29: 43556
A30: 43586
A31: 43617
A32: 43647
A33: 43678
A34: 43709
A35: 43739
A36: 43770
A37: 43800

Sheet EBITDA
A1: EBITDA | G1: Lata: | H1: ='Ogólny '!R4 -> 2024
A23: UWAGA - jeśli istnieje osobny plan działania lub opracowany dokument analizy przyczyny pierwotnej, w komórce "Komentarze" wystarczy przywołać dany dokument (nie ma potrzeby powielania informacji i działań).
A25: Miesiąc | B25: Czy osiągnięto cel? | C25: Czy wymagane są działania? | D25: Opis problemu | E25: Główna przyczyna | F25: Opis działań | G25: Odpowiedzialność | H25: Data zakończenia | J25: Komentarze | K25: Status (OTWARTY/ ZAMKNIĘTY)
A26: 43466
A27: 43497
A28: 43525
A29: 43556
A30: 43586
A31: 43617
A32: 43647
A33: 43678
A34: 43709
A35: 43739
A36: 43770
A37: 43800

Sheet CAPEX
A1: CAPEX | G1: Lata: | H1: ='Ogólny '!R4 -> 2024
A23: UWAGA - jeśli istnieje osobny plan działania lub opracowany dokument analizy przyczyny pierwotnej, w komórce "Komentarze" wystarczy przywołać dany dokument (nie ma potrzeby powielania informacji i działań).
A25: Miesiąc | B25: Czy osiągnięto cel? | C25: Czy wymagane są działania? | D25: Opis problemu | E25: Główna przyczyna | F25: Opis działań | G25: Odpowiedzialność | H25: Data zakończenia | J25: Komentarze | K25: Status (OTWARTY/ ZAMKNIĘTY)
A26: 43466
A27: 43497
A28: 43525
A29: 43556
A30: 43586
A31: 43617
A32: 43647
A33: 43678
A34: 43709
A35: 43739
A36: 43770
A37: 43800

Sheet Zwroty od klienta
A1: Zwroty od klienta | G1: Lata: | H1: ='Ogólny '!R4 -> 2024
A23: UWAGA - jeśli istnieje osobny plan działania lub opracowany dokument analizy przyczyny pierwotnej, w komórce "Komentarze" wystarczy przywołać dany dokument (nie ma potrzeby powielania informacji i działań).
A25: Miesiąc | B25: Czy osiągnięto cel? | C25: Czy wymagane są działania? | D25: Opis problemu | E25: Główna przyczyna | F25: Opis działań | G25: Odpowiedzialność | H25: Data zakończenia | J25: Komentarze | K25: Status (OTWARTY/ ZAMKNIĘTY)
A26: 43466
A27: 43497
A28: 43525
A29: 43556
A30: 43586
A31: 43617
A32: 43647
A33: 43678
A34: 43709
A35: 43739
A36: 43770
A37: 43800

Sheet Wymiana u klienta
A1: Wymiana u klienta | G1: Lata: | H1: ='Ogólny '!R4 -> 2024
A23: UWAGA - jeśli istnieje osobny plan działania lub opracowany dokument analizy przyczyny pierwotnej, w komórce "Komentarze" wystarczy przywołać dany dokument (nie ma potrzeby powielania informacji i działań).
A25: Miesiąc | B25: Czy osiągnięto cel? | C25: Czy wymagane są działania? | D25: Opis problemu | E25: Główna przyczyna | F25: Opis działań | G25: Odpowiedzialność | H25: Data zakończenia | J25: Komentarze | K25: Status (OTWARTY/ ZAMKNIĘTY)
A26: 43466
A27: 43497
A28: 43525
A29: 43556
A30: 43586
A31: 43617
A32: 43647
A33: 43678
A34: 43709
A35: 43739
A36: 43770
A37: 43800

Sheet Zwroty klientów (wewnętrzne)
A1: Zwroty klientów (wewnętrzne) | G1: Lata: | H1: ='Ogólny '!R4 -> 2024
A23: UWAGA - jeśli istnieje osobny plan działania lub opracowany dokument analizy przyczyny pierwotnej, w komórce "Komentarze" wystarczy przywołać dany dokument (nie ma potrzeby powielania informacji i działań).
A25: Miesiąc | B25: Czy osiągnięto cel? | C25: Czy wymagane są działania? | D25: Opis problemu | E25: Główna przyczyna | F25: Opis działań | G25: Odpowiedzialność | H25: Data zakończenia | J25: Komentarze | K25: Status (OTWARTY/ ZAMKNIĘTY)
A26: 43466
A27: 43497
A28: 43525
A29: 43556
A30: 43586
A31: 43617
A32: 43647
A33: 43678
A34: 43709
A35: 43739
A36: 43770
A37: 43800

Sheet Poziom Backlog
A1: Poziom Backlog | G1: Lata: | H1: ='Ogólny '!R4 -> 2024
A23: UWAGA - jeśli istnieje osobny plan działania lub opracowany dokument analizy przyczyny pierwotnej, w komórce "Komentarze" wystarczy przywołać dany dokument (nie ma potrzeby powielania informacji i działań).
A25: Miesiąc | B25: Czy osiągnięto cel? | C25: Czy wymagane są działania? | D25: Opis problemu | E25: Główna przyczyna | F25: Opis działań | G25: Odpowiedzialność | H25: Data zakończenia | J25: Komentarze | K25: Status (OTWARTY/ ZAMKNIĘTY)
A26: 43466
A27: 43497
A28: 43525
A29: 43556
A30: 43586
A31: 43617
A32: 43647
A33: 43678
A34: 43709
A35: 43739
A36: 43770
A37: 43800

Sheet Dostawy na czas
A1: Dostawy na czas | G1: Lata: | H1: ='Ogólny '!R4 -> 2024
A23: UWAGA - jeśli istnieje osobny plan działania lub opracowany dokument analizy przyczyny pierwotnej, w komórce "Komentarze" wystarczy przywołać dany dokument (nie ma potrzeby powielania informacji i działań).
A25: Miesiąc | B25: Czy osiągnięto cel? | C25: Czy wymagane są działania? | D25: Opis problemu | E25: Główna przyczyna | F25: Opis działań | G25: Odpowiedzialność | H25: Data zakończenia | J25: Komentarze | K25: Status (OTWARTY/ ZAMKNIĘTY)
A26: 43466
A27: 43497
A28: 43525
A29: 43556
A30: 43586
A31: 43617
A32: 43647
A33: 43678
A34: 43709
A35: 43739
A36: 43770
A37: 43800

Sheet OEE
A1: OEE na kluczowych stanowiskach (legalizacja mieszkaniowe) | G1: Lata: | H1: ='Ogólny '!R4 -> 2024
A23: UWAGA - jeśli istnieje osobny plan działania lub opracowany dokument analizy przyczyny pierwotnej, w komórce "Komentarze" wystarczy przywołać dany dokument (nie ma potrzeby powielania informacji i działań).
A25: Miesiąc | B25: Czy osiągnięto cel? | C25: Czy wymagane są działania? | D25: Opis problemu | E25: Główna przyczyna | F25: Opis działań | G25: Odpowiedzialność | H25: Data zakończenia | J25: Komentarze | K25: Status (OTWARTY/ ZAMKNIĘTY)
A26: 43466
A27: 43497
A28: 43525
A29: 43556
A30: 43586
A31: 43617
A32: 43647
A33: 43678
A34: 43709
A35: 43739
A36: 43770
A37: 43800

Sheet WIP
A1: WIP | G1: Lata: | H1: ='Ogólny '!R4 -> 2024
A23: UWAGA - jeśli istnieje osobny plan działania lub opracowany dokument analizy przyczyny pierwotnej, w komórce "Komentarze" wystarczy przywołać dany dokument (nie ma potrzeby powielania informacji i działań).
A25: Miesiąc | B25: Czy osiągnięto cel? | C25: Czy wymagane są działania? | D25: Opis problemu | E25: Główna przyczyna | F25: Opis działań | G25: Odpowiedzialność | H25: Data zakończenia | J25: Komentarze | K25: Status (OTWARTY/ ZAMKNIĘTY)
A26: 43466
A27: 43497
A28: 43525
A29: 43556
A30: 43586
A31: 43617
A32: 43647
A33: 43678
A34: 43709
A35: 43739
A36: 43770
A37: 43800

Sheet Materiał
A1: Materiał | G1: Lata: | H1: ='Ogólny '!R4 -> 2024
A23: UWAGA - jeśli istnieje osobny plan działania lub opracowany dokument analizy przyczyny pierwotnej, w komórce "Komentarze" wystarczy przywołać dany dokument (nie ma potrzeby powielania informacji i działań).
A25: Miesiąc | B25: Czy osiągnięto cel? | C25: Czy wymagane są działania? | D25: Opis problemu | E25: Główna przyczyna | F25: Opis działań | G25: Odpowiedzialność | H25: Data zakończenia | J25: Komentarze | K25: Status (OTWARTY/ ZAMKNIĘTY)
A26: 43466
A27: 43497
A28: 43525
A29: 43556
A30: 43586
A31: 43617
A32: 43647
A33: 43678
A34: 43709
A35: 43739
A36: 43770
A37: 43800

Sheet Wyroby gotowe
A1: Wyroby gotowe | G1: Lata: | H1: ='Ogólny '!R4 -> 2024
A23: UWAGA - jeśli istnieje osobny plan działania lub opracowany dokument analizy przyczyny pierwotnej, w komórce "Komentarze" wystarczy przywołać dany dokument (nie ma potrzeby powielania informacji i działań).
A25: Miesiąc | B25: Czy osiągnięto cel? | C25: Czy wymagane są działania? | D25: Opis problemu | E25: Główna przyczyna | F25: Opis działań | G25: Odpowiedzialność | H25: Data zakończenia | J25: Komentarze | K25: Status (OTWARTY/ ZAMKNIĘTY)
A26: 43466
A27: 43497
A28: 43525
A29: 43556
A30: 43586
A31: 43617
A32: 43647
A33: 43678
A34: 43709
A35: 43739
A36: 43770
A37: 43800

Sheet Towary
A1: Towary | G1: Lata: | H1: ='Ogólny '!R4 -> 2024
A23: UWAGA - jeśli istnieje osobny plan działania lub opracowany dokument analizy przyczyny pierwotnej, w komórce "Komentarze" wystarczy przywołać dany dokument (nie ma potrzeby powielania informacji i działań).
A25: Miesiąc | B25: Czy osiągnięto cel? | C25: Czy wymagane są działania? | D25: Opis problemu | E25: Główna przyczyna | F25: Opis działań | G25: Odpowiedzialność | H25: Data zakończenia | J25: Komentarze | K25: Status (OTWARTY/ ZAMKNIĘTY)
A26: 43466
A27: 43497
A28: 43525
A29: 43556
A30: 43586
A31: 43617
A32: 43647
A33: 43678
A34: 43709
A35: 43739
A36: 43770
A37: 43800

Sheet Współczynnik rotacji
A1: Współczynnik rotacji | G1: Lata: | H1: ='Ogólny '!R4 -> 2024
A23: UWAGA - jeśli istnieje osobny plan działania lub opracowany dokument analizy przyczyny pierwotnej, w komórce "Komentarze" wystarczy przywołać dany dokument (nie ma potrzeby powielania informacji i działań).
A25: Miesiąc | B25: Czy osiągnięto cel? | C25: Czy wymagane są działania? | D25: Opis problemu | E25: Główna przyczyna | F25: Opis działań | G25: Odpowiedzialność | H25: Data zakończenia | J25: Komentarze | K25: Status (OTWARTY/ ZAMKNIĘTY)
A26: 43466
A27: 43497
A28: 43525
A29: 43556
A30: 43586
A31: 43617
A32: 43647
A33: 43678
A34: 43709
A35: 43739
A36: 43770
A37: 43800

Sheet Absencja
A1: Absencja | G1: Lata: | H1: ='Ogólny '!R4 -> 2024
A23: UWAGA - jeśli istnieje osobny plan działania lub opracowany dokument analizy przyczyny pierwotnej, w komórce "Komentarze" wystarczy przywołać dany dokument (nie ma potrzeby powielania informacji i działań).
A25: Miesiąc | B25: Czy osiągnięto cel? | C25: Czy wymagane są działania? | D25: Opis problemu | E25: Główna przyczyna | F25: Opis działań | G25: Odpowiedzialność | H25: Data zakończenia | J25: Komentarze | K25: Status (OTWARTY/ ZAMKNIĘTY)
A26: 43466
A27: 43497
A28: 43525
A29: 43556
A30: 43586
A31: 43617
A32: 43647
A33: 43678
A34: 43709
A35: 43739
A36: 43770
A37: 43800

Sheet Poziom zaległych ulopów
A1: Poziom zaległych urlopów | G1: Lata: | H1: ='Ogólny '!R4 -> 2024
A23: UWAGA - jeśli istnieje osobny plan działania lub opracowany dokument analizy przyczyny pierwotnej, w komórce "Komentarze" wystarczy przywołać dany dokument (nie ma potrzeby powielania informacji i działań).
A25: Miesiąc | B25: Czy osiągnięto cel? | C25: Czy wymagane są działania? | D25: Opis problemu | E25: Główna przyczyna | F25: Opis działań | G25: Odpowiedzialność | H25: Data zakończenia | J25: Komentarze | K25: Status (OTWARTY/ ZAMKNIĘTY)
A26: 43466
A27: 43497
A28: 43525
A29: 43556
A30: 43586
A31: 43617
A32: 43647
A33: 43678
A34: 43709
A35: 43739
A36: 43770
A37: 43800

Sheet Ilość wypadków
A1: Ilość wypadków | G1: Lata: | H1: ='Ogólny '!R4 -> 2024
A23: UWAGA - jeśli istnieje osobny plan działania lub opracowany dokument analizy przyczyny pierwotnej, w komórce "Komentarze" wystarczy przywołać dany dokument (nie ma potrzeby powielania informacji i działań).
A25: Miesiąc | B25: Czy osiągnięto cel? | C25: Czy wymagane są działania? | D25: Opis problemu | E25: Główna przyczyna | F25: Opis działań | G25: Odpowiedzialność | H25: Data zakończenia | J25: Komentarze | K25: Status (OTWARTY/ ZAMKNIĘTY)
A26: 43466
A27: 43497
A28: 43525
A29: 43556
A30: 43586
A31: 43617
A32: 43647
A33: 43678
A34: 43709
A35: 43739
A36: 43770
A37: 43800

Sheet Zużycie energii elektrycznej
A1: Zużycie energii elektrycznej | G1: Lata: | H1: ='Ogólny '!R4 -> 2024
A23: UWAGA - jeśli istnieje osobny plan działania lub opracowany dokument analizy przyczyny pierwotnej, w komórce "Komentarze" wystarczy przywołać dany dokument (nie ma potrzeby powielania informacji i działań).
A25: Miesiąc | B25: Czy osiągnięto cel? | C25: Czy wymagane są działania? | D25: Opis problemu | E25: Główna przyczyna | F25: Opis działań | G25: Odpowiedzialność | H25: Data zakończenia | J25: Komentarze | K25: Status (OTWARTY/ ZAMKNIĘTY)
A26: 43466
A27: 43497
A28: 43525
A29: 43556
A30: 43586
A31: 43617
A32: 43647
A33: 43678
A34: 43709
A35: 43739
A36: 43770
A37: 43800

Sheet Zużycie wody
A1: Zużycie wody | G1: Lata: | H1: ='Ogólny '!R4 -> 2024
A23: UWAGA - jeśli istnieje osobny plan działania lub opracowany dokument analizy przyczyny pierwotnej, w komórce "Komentarze" wystarczy przywołać dany dokument (nie ma potrzeby powielania informacji i działań).
A25: Miesiąc | B25: Czy osiągnięto cel? | C25: Czy wymagane są działania? | D25: Opis problemu | E25: Główna przyczyna | F25: Opis działań | G25: Odpowiedzialność | H25: Data zakończenia | J25: Komentarze | K25: Status (OTWARTY/ ZAMKNIĘTY)
A26: 43466
A27: 43497
A28: 43525
A29: 43556
A30: 43586
A31: 43617
A32: 43647
A33: 43678
A34: 43709
A35: 43739
A36: 43770
A37: 43800

Sheet UR
C3: Do wprowadzenia
